tracllm_kit/__init__.py
tracllm_kit/prompts.py
tracllm_kit/utils.py
tracllm_kit/attribution/__init__.py
tracllm_kit/attribution/attribute.py
tracllm_kit/attribution/perturbation_based.py
tracllm_kit/attribution/self_citation.py
tracllm_kit/models/GPT.py
tracllm_kit/models/HF_model.py
tracllm_kit/models/Llama.py
tracllm_kit/models/Model.py
tracllm_kit/models/__init__.py
tracllm_kit-0.1.2.dist-info/LICENSE
tracllm_kit-0.1.2.dist-info/METADATA
tracllm_kit-0.1.2.dist-info/WHEEL
tracllm_kit-0.1.2.dist-info/top_level.txt
tracllm_kit-0.1.2.dist-info/RECORD
